HISTORY.rst
LICENSE.rst
MANIFEST.in
README.rst
setup.py
src/bda/__init__.py
src/bda.plone.wfintranet.egg-info/PKG-INFO
src/bda.plone.wfintranet.egg-info/SOURCES.txt
src/bda.plone.wfintranet.egg-info/dependency_links.txt
src/bda.plone.wfintranet.egg-info/entry_points.txt
src/bda.plone.wfintranet.egg-info/namespace_packages.txt
src/bda.plone.wfintranet.egg-info/not-zip-safe
src/bda.plone.wfintranet.egg-info/requires.txt
src/bda.plone.wfintranet.egg-info/top_level.txt
src/bda/plone/__init__.py
src/bda/plone/wfintranet/__init__.py
src/bda/plone/wfintranet/configure.zcml
src/bda/plone/wfintranet/sharing.py
src/bda/plone/wfintranet/profile/metadata.xml
src/bda/plone/wfintranet/profile/rolemap.xml
src/bda/plone/wfintranet/profile/workflows.xml
src/bda/plone/wfintranet/profile/workflows/bda_intranet_workflow/definition.xml