Metadata-Version: 1.0
Name: bda.plone.wfintranet
Version: 1.0
Summary: Intranet Workflow by Bluedynamics Alliance
Home-page: UNKNOWN
Author: BlueDynamics Alliance
Author-email: dev@bluedynamics.com
License: General Public Licence
Platform: UNKNOWN
Classifier: Environment :: Web Environment
Classifier: License :: OSI Approved :: GNU General Public License (GPL)
Classifier: Operating System :: OS Independent
Classifier: Programming Language :: Python
Classifier: Topic :: Internet :: WWW/HTTP :: Dynamic Content
